MANIFEST.in
README.md
setup.py
netbox_pool_manager.egg-info/PKG-INFO
netbox_pool_manager.egg-info/SOURCES.txt
netbox_pool_manager.egg-info/dependency_links.txt
netbox_pool_manager.egg-info/not-zip-safe
netbox_pool_manager.egg-info/top_level.txt
pool_manager/__init__.py
pool_manager/filtersets.py
pool_manager/forms.py
pool_manager/graphql.py
pool_manager/models.py
pool_manager/navigation.py
pool_manager/search.py
pool_manager/tables.py
pool_manager/urls.py
pool_manager/version.py
pool_manager/views.py
pool_manager/api/__init__.py
pool_manager/api/serializers.py
pool_manager/api/urls.py
pool_manager/api/views.py
pool_manager/migrations/0001_initial.py
pool_manager/migrations/0002_pool_poollease_poolmembers_and_more.py
pool_manager/migrations/0003_alter_pool_range.py
pool_manager/migrations/0004_alter_pool_range.py
pool_manager/migrations/0005_alter_poollease_options_rename_pool3_poollease_pool_and_more.py
pool_manager/migrations/0006_rename_pool_member2_poollease_pool_member_and_more.py
pool_manager/migrations/0007_remove_poollease_pool_member.py
pool_manager/migrations/0008_rename_poolmembers_poolmember.py
pool_manager/migrations/0009_alter_poolmember_options_remove_poolmember_lease_and_more.py
pool_manager/migrations/0010_alter_poolmember_options_poolmember_pool_and_more.py
pool_manager/migrations/0011_alter_poolmember_options_and_more.py
pool_manager/migrations/0012_alter_poolmember_options_and_more.py
pool_manager/migrations/0013_alter_poolmember_pool.py
pool_manager/migrations/0014_alter_poollease_options_and_more.py
pool_manager/migrations/0015_alter_poollease_range_number.py
pool_manager/migrations/0016_alter_poollease_range_number.py
pool_manager/migrations/0017_alter_poollease_range_number.py
pool_manager/migrations/0018_alter_poollease_range_number.py
pool_manager/migrations/0019_remove_poollease_app_type_and_more.py
pool_manager/migrations/0020_alter_pool_range.py
pool_manager/migrations/0021_alter_pool_algorithm_and_index.py
pool_manager/migrations/0022_alter_poollease_tags.py
pool_manager/migrations/0023_alter_pool_range.py
pool_manager/migrations/__init__.py
pool_manager/templates/pool_manager/pool.html
pool_manager/templates/pool_manager/poollease.html