Metadata-Version: 2.1
Name: netbox_pool_manager
Version: 1.1.0
Summary: An Pool Manager NetBox plugin
